neurokernel/__init__.py
neurokernel/all_global_vars.py
neurokernel/core.py
neurokernel/core_gpu.py
neurokernel/core_gpu_onesided.py
neurokernel/ctx_managers.py
neurokernel/mixins.py
neurokernel/mpi.py
neurokernel/mpi_backend.py
neurokernel/mpi_proc.py
neurokernel/mpi_relaunch.py
neurokernel/pattern.py
neurokernel/plsel.py
neurokernel/pm.py
neurokernel/pm_gpu.py
neurokernel/routing_table.py
neurokernel/stats.py
neurokernel/uid.py
neurokernel/version.py
neurokernel/neuroml/__init__.py
neurokernel/neuroml/config.py
neurokernel/neuroml/generateds_config.py
neurokernel/neuroml/helper_methods.py
neurokernel/neuroml/nml.py
neurokernel/neuroml/utils.py
neurokernel/tools/__init__.py
neurokernel/tools/autoinit.py
neurokernel/tools/gpu.py
neurokernel/tools/graph.py
neurokernel/tools/logging.py
neurokernel/tools/misc.py
neurokernel/tools/mpi.py
neurokernel/tools/mpi_run.py
neurokernel/tools/plot.py
neurokernel/tools/timing.py
neurokernel/tools/zmq.py
nk/__init__.py
neurokernel-0.3.1.dist-info/AUTHORS.rst
neurokernel-0.3.1.dist-info/LICENSE.rst
neurokernel-0.3.1.dist-info/METADATA
neurokernel-0.3.1.dist-info/WHEEL
neurokernel-0.3.1.dist-info/top_level.txt
neurokernel-0.3.1.dist-info/RECORD
