Metadata-Version: 2.1
Name: neurokernel
Version: 0.3.1
Summary: An open architecture for Drosophila brain emulation
Home-page: https://github.com/neurokernel/neurokernel/
Author: Neurokernel Development Team
Author-email: neurokernel-dev@columbia.edu
Maintainer: Neurokernel Development Team
Maintainer-email: neurokernel-dev@columbia.edu
License: BSD
Platform: UNKNOWN
Classifier: Development Status :: 3 - Alpha
Classifier: Intended Audience :: Developers
Classifier: Intended Audience :: Science/Research
Classifier: License :: OSI Approved :: BSD License
Classifier: Operating System :: OS Independent
Classifier: Programming Language :: Python
Classifier: Topic :: Scientific/Engineering
Classifier: Topic :: Software Development
Requires-Dist: bidict (>=0.11.0)
Requires-Dist: dill (<=0.3.3,>=0.2.4)
Requires-Dist: future (>=0.16.0)
Requires-Dist: h5py (>=2.8.0)
Requires-Dist: lxml (>=3.3.0)
Requires-Dist: markupsafe (>=0.23)
Requires-Dist: matplotlib (>=1.4.3)
Requires-Dist: mpi4py (>=1.3.1)
Requires-Dist: networkx (>=2.4)
Requires-Dist: numexpr (>=2.3)
Requires-Dist: numpy (>=1.9.2)
Requires-Dist: pandas (>=1.0.0)
Requires-Dist: ply (>=3.4)
Requires-Dist: psutil (>=2.2.1)
Requires-Dist: pycuda (>=2020.1)
Requires-Dist: scipy (>=0.11.0)
Requires-Dist: shutilwhich (>=1.1.0)
Requires-Dist: twiggy (>=0.4.7)
Requires-Dist: tqdm
Requires-Dist: futures ; python_version == "2.7"
Provides-Extra: sphinx
Requires-Dist: sphinx (>=1.3) ; extra == 'sphinx'
Provides-Extra: sphinx_rtd_theme
Requires-Dist: sphinx-rtd-theme (>=0.1.6) ; extra == 'sphinx_rtd_theme'
